data_cipher/__init__.py
data_cipher/encoder.py
data_cipher-0.0.2.dist-info/LICENSE
data_cipher-0.0.2.dist-info/METADATA
data_cipher-0.0.2.dist-info/WHEEL
data_cipher-0.0.2.dist-info/top_level.txt
data_cipher-0.0.2.dist-info/RECORD
