Metadata-Version: 2.1
Name: data-cipher
Version: 0.0.2
Summary: Encrypting and Decrypting data
Home-page: UNKNOWN
Author: Dronikon (Nikita Derevyankin)
Author-email: <dronikosha@gmail.com>
License: UNKNOWN
Keywords: python,encrypt,decrypt,aes,blowfish
Platform: UNKNOWN
Classifier: Development Status :: 1 - Planning
Classifier: Intended Audience :: Developers
Classifier: Programming Language :: Python :: 3
Classifier: Operating System :: Unix
Classifier: Operating System :: MacOS :: MacOS X
Classifier: Operating System :: Microsoft :: Windows
License-File: LICENSE
Requires-Dist: pycryptodome
